{"version":1,"resource":"vscode-remote://abdallahdev-websitestar-esjdme0laxn.ws-eu120.gitpod.io/workspace/Website-starter/src/components/ui/stars/FullStar.astro","entries":[{"id":"ez7j.astro","timestamp":1754577013550},{"id":"mASD.astro","timestamp":1754585771226},{"id":"VHlu.astro","timestamp":1754585792246},{"id":"KRBy.astro","timestamp":1754585813662},{"id":"IXJK.astro","timestamp":1754607880703},{"id":"0YcQ.astro","timestamp":1754607891851},{"id":"gY56.astro","timestamp":1754749996059},{"id":"VHwi.astro","timestamp":1754750017223}]}